{"resourceType":"Questionnaire","language":"nb-NO","id":"68","name":"NHN_Testskjema_Dato","title":"Testskjema dato","version":"1.0","status":"draft","publisher":"NHN","meta":{"profile":["http://ehelse.no/fhir/StructureDefinition/sdf-Questionnaire"],"tag":[{"system":"urn:ietf:bcp:47","code":"nb-NO","display":"Norsk bokmål"}],"security":[{"code":"3","display":"Helsehjelp (Full)","system":"urn:oid:2.16.578.1.12.4.1.1.7618"}]},"useContext":[{"code":{"system":"http://hl7.org/fhir/ValueSet/usage-context-type","code":"focus","display":"Clinical Focus"},"valueCodeableConcept":{"coding":[{"system":"urn:oid:2.16.578.1.12.4.1.1.8655","code":"S","display":"Helsehjelp knyttet til somatisk sykdom"}]}}],"subjectType":["Person"],"extension":[{"url":"http://ehelse.no/fhir/StructureDefinition/sdf-accessibilitytoresponse","valueCoding":{"system":"http://ehelse.no/fhir/ValueSet/AccessibilityToResponse","code":"1"}},{"url":"http://ehelse.no/fhir/StructureDefinition/sdf-discretion","valueCoding":{"system":"http://ehelse.no/fhir/ValueSet/Discretion","code":"0"}},{"url":"http://ehelse.no/fhir/StructureDefinition/sdf-generatepdf","valueBoolean":true},{"url":"http://ehelse.no/fhir/StructureDefinition/sdf-generatenarrative","valueBoolean":true},{"url":"http://helsenorge.no/fhir/StructureDefinition/sdf-presentationbuttons","valueCoding":{"system":"http://helsenorge.no/fhir/ValueSet/presentationbuttons","code":"sticky"}},{"url":"http://ehelse.no/fhir/StructureDefinition/sdf-authenticationrequirement","valueCoding":{"system":"http://ehelse.no/fhir/ValueSet/AuthenticationRequirement","code":"3"}}],"copyright":"Er utviklet av NHN","date":"2020-10-23","item":[{"linkId":"1","text":"Informasjon","type":"group","repeats":false,"item":[{"linkId":"1.100","text":"Om skjemaet","type":"group","repeats":false,"item":[{"linkId":"1.100.100","text":"Testskjema dato","type":"display"}]}]},{"linkId":"2","text":"Datetime","type":"group","repeats":false,"item":[{"extension":[{"url":"http://ehelse.no/fhir/StructureDefinition/validationtext","valueString":"Du må velge en dato og et klokkeslett"}],"linkId":"2.1","text":"Velg dato og klokkeslett","type":"dateTime","required":true,"repeats":false,"readOnly":false}]},{"linkId":"3","text":"Time","type":"group","repeats":false,"item":[{"extension":[{"url":"http://ehelse.no/fhir/StructureDefinition/validationtext","valueString":"Du må velge et klokkeslett"}],"linkId":"3.1","text":"Velg klokkeslett","type":"time","required":true,"repeats":false,"readOnly":false}]},{"linkId":"4","text":"Date","type":"group","repeats":false,"item":[{"extension":[{"url":"http://ehelse.no/fhir/StructureDefinition/validationtext","valueString":"Du må velge år, måned og dag"}],"linkId":"4.1","text":"Velg år, måned og dag","type":"date","required":true,"repeats":false,"readOnly":false}]},{"linkId":"5","text":"Date med utvidelser","type":"group","repeats":false,"item":[{"extension":[{"url":"http://ehelse.no/fhir/StructureDefinition/validationtext","valueString":"Du må velge år"},{"url":"http://hl7.org/fhir/StructureDefinition/questionnaire-itemControl","valueCodeableConcept":{"coding":[{"system":"http://hl7.org/fhir/ValueSet/questionnaire-item-control","code":"year"}]}}],"linkId":"5.1","text":"Velg år","type":"date","required":true,"repeats":false,"readOnly":false},{"extension":[{"url":"http://ehelse.no/fhir/StructureDefinition/validationtext","valueString":"Du må velge år og måned"},{"url":"http://hl7.org/fhir/StructureDefinition/questionnaire-itemControl","valueCodeableConcept":{"coding":[{"system":"http://hl7.org/fhir/ValueSet/questionnaire-item-control","code":"yearMonth"}]}}],"linkId":"5.2","text":"Velg år og måned","type":"date","required":true,"repeats":false,"readOnly":false},{"extension":[{"url":"http://ehelse.no/fhir/StructureDefinition/validationtext","valueString":"Du må velge måned"},{"url":"http://hl7.org/fhir/StructureDefinition/questionnaire-itemControl","valueCodeableConcept":{"coding":[{"system":"http://hl7.org/fhir/ValueSet/questionnaire-item-control","code":"month"}]}}],"linkId":"5.3","text":"Velg måned","type":"date","required":true,"repeats":false,"readOnly":false},{"extension":[{"url":"http://ehelse.no/fhir/StructureDefinition/validationtext","valueString":"Du må velge dag"},{"url":"http://hl7.org/fhir/StructureDefinition/questionnaire-itemControl","valueCodeableConcept":{"coding":[{"system":"http://hl7.org/fhir/ValueSet/questionnaire-item-control","code":"day"}]}}],"linkId":"5.4","text":"Velg dag","type":"date","required":true,"repeats":false,"readOnly":false}]},{"linkId":"6","text":"Date med validering","type":"group","repeats":false,"item":[{"extension":[{"url":"http://ehelse.no/fhir/StructureDefinition/validationtext","valueString":"Velg dato, eller skriv dato på denne måten: dd.mm.åååå. Dato må være større enn dagens dato."},{"url":"http://ehelse.no/fhir/StructureDefinition/sdf-fhirpathvalidation","valueString":"this.value >= today()"},{"url":"http://ehelse.no/fhir/StructureDefinition/sdf-minvalue","valueString":"today()"}],"linkId":"6.1","text":"Forventet termin","type":"date","required":true,"repeats":false,"readOnly":false},{"extension":[{"url":"http://ehelse.no/fhir/StructureDefinition/validationtext","valueString":"Velg dato, eller skriv dato på denne måten: dd.mm.åååå. Dato må være mindre enn dagens dato."},{"url":"http://ehelse.no/fhir/StructureDefinition/sdf-fhirpathvalidation","valueString":"this.value <= today()"},{"url":"http://ehelse.no/fhir/StructureDefinition/sdf-maxvalue","valueString":"today()"}],"linkId":"6.2","text":"Når var siste menstruasjon?","type":"date","required":true,"repeats":false,"readOnly":false},{"extension":[{"url":"http://ehelse.no/fhir/StructureDefinition/validationtext","valueString":"Du kan velge en dato fra i dag og 7 dager tilbake i tid. Dato skal ha format dd.mm.åååå."},{"url":"http://ehelse.no/fhir/StructureDefinition/sdf-fhirpathvalidation","valueString":"this.value <= today()  and this.value >=today() - 7 days"},{"url":"http://ehelse.no/fhir/StructureDefinition/sdf-maxvalue","valueString":"today()"},{"url":"http://ehelse.no/fhir/StructureDefinition/sdf-minvalue","valueString":"today() - 7 days"}],"linkId":"6.3","text":"Hvilken dag fikk du symptomer?","type":"date","required":true,"repeats":false,"readOnly":false},{"extension":[{"url":"http://ehelse.no/fhir/StructureDefinition/validationtext","valueString":"Velg dato, eller skriv dato på denne måten: dd.mm.åååå."},{"url":"http://ehelse.no/fhir/StructureDefinition/sdf-minvalue","valueString":"@2020-10-01"}],"linkId":"6.4","text":"Min date med fhir path","type":"date","required":true,"repeats":false,"readOnly":false},{"extension":[{"url":"http://ehelse.no/fhir/StructureDefinition/validationtext","valueString":"Velg dato, eller skriv dato på denne måten: dd.mm.åååå."},{"url":"http://ehelse.no/fhir/StructureDefinition/sdf-maxvalue","valueString":"@2020-11-01"}],"linkId":"6.5","text":"Max date med fhir path","type":"date","required":true,"repeats":false,"readOnly":false},{"extension":[{"url":"http://ehelse.no/fhir/StructureDefinition/validationtext","valueString":"Velg dato, eller skriv dato på denne måten: dd.mm.åååå."},{"url":"http://ehelse.no/fhir/StructureDefinition/sdf-maxvalue","valueString":"@2020-11-01"},{"url":"http://ehelse.no/fhir/StructureDefinition/sdf-minvalue","valueString":"@2020-10-01"}],"linkId":"6.6","text":"Max og min date med fhir path","type":"date","required":true,"repeats":false,"readOnly":false},{"extension":[{"url":"http://ehelse.no/fhir/StructureDefinition/validationtext","valueString":"Velg dato, eller skriv dato på denne måten: dd.mm.åååå."}],"linkId":"6.7","text":"Initial date gammel måte","type":"date","required":true,"repeats":false,"readOnly":false,"initial":[{"valueDate":"2020-10-23"}]},{"extension":[{"url":"http://ehelse.no/fhir/StructureDefinition/validationtext","valueString":"Velg dato, eller skriv dato på denne måten: dd.mm.åååå."},{"url":"http://hl7.org/fhir/StructureDefinition/minValue","valueDateTime":"2020-10-22T22:00:00+00:00"}],"linkId":"6.8","text":"Min dato gammel måte","type":"date","required":true,"repeats":false,"readOnly":false},{"extension":[{"url":"http://ehelse.no/fhir/StructureDefinition/validationtext","valueString":"Velg dato, eller skriv dato på denne måten: dd.mm.åååå."},{"url":"http://hl7.org/fhir/StructureDefinition/maxValue","valueDateTime":"2020-10-29T23:00:00+00:00"}],"linkId":"6.9","text":"Max dato gammel måte","type":"date","required":true,"repeats":false,"readOnly":false},{"extension":[{"url":"http://ehelse.no/fhir/StructureDefinition/validationtext","valueString":"Velg dato, eller skriv dato på denne måten: dd.mm.åååå."},{"url":"http://hl7.org/fhir/StructureDefinition/maxValue","valueDateTime":"2020-10-29T23:00:00+00:00"},{"url":"http://hl7.org/fhir/StructureDefinition/minValue","valueDateTime":"2020-10-22T22:00:00+00:00"}],"linkId":"6.10","text":"Min og max dato gammel måte","type":"date","required":true,"repeats":false,"readOnly":false}]},{"linkId":"7","text":"Tada!!","type":"group","repeats":false,"item":[{"linkId":"7.1","text":"Takk for hjelpen!","type":"display"}]}]}